mud/MUDIndexerSDK.py
mud/Player.py
mud/World.py
mud/__init__.py
mud_aw.py-0.14.dist-info/LICENSE
mud_aw.py-0.14.dist-info/METADATA
mud_aw.py-0.14.dist-info/WHEEL
mud_aw.py-0.14.dist-info/top_level.txt
mud_aw.py-0.14.dist-info/RECORD
