Metadata-Version: 2.1
Name: mud-aw.py
Version: 0.14
Summary: Python API for interacting with MUD Autonomous Worlds
Home-page: https://github.com/officialnico/mud-aw.py
Author: Nico Rodriguez
License: MIT
Platform: UNKNOWN
Classifier: Programming Language :: Python :: 3
Classifier: License :: OSI Approved :: MIT License
Classifier: Operating System :: OS Independent
Requires-Python: >=3.6
License-File: LICENSE
Requires-Dist: requests>=2.25.1
Requires-Dist: web3
Requires-Dist: dotenv
Requires-Dist: pandas
Requires-Dist: IPython
